{"_type":"export","__export_format":4,"__export_date":"2024-07-30T21:03:20.899Z","__export_source":"insomnia.desktop.app:v9.3.2","resources":[{"_id":"req_3fdbe257148d4fad84af496696dc3cd5","parentId":"fld_7eb1d9f0f3264eba9f8747ac46d1040f","modified":1722373276784,"created":1722355207200,"url":"http://localhost:4000/produtos","name":"Cadastrar Produto","description":"","method":"POST","body":{"mimeType":"application/json","text":"{\n    \"nome\": \"Introdução à lógica de programação e algoritmos\",\n    \"descricao\": \"Aprenda os fundamentos da lógica de programação e algoritmos. O curso cobre conceitos básicos de programação, como estruturas de controle e resolução de problemas, ajudando você a desenvolver habilidades para criar soluções eficientes e organizar o raciocínio lógico necessário para programar.\",\n    \"preco\": 29.90,\n    \"duracao\": 60,\n\t  \"foto\": \"https://ik.imagekit.io/netdmdufko/logica.jpg?updatedAt=1722359434707\",\n\t\"categoria\": {\n\t\"id\": 1\n}\n}"},"parameters":[],"headers":[{"name":"Content-Type","value":"application/json"},{"name":"User-Agent","value":"insomnia/9.3.2"}],"authentication":{},"metaSortKey":-1722355207200,"isPrivate":false,"pathParameters":[],"settingStoreCookies":true,"settingSendCookies":true,"settingDisableRenderRequestBody":false,"settingEncodeUrl":true,"settingRebuildPath":true,"settingFollowRedirects":"global","_type":"request"},{"_id":"fld_7eb1d9f0f3264eba9f8747ac46d1040f","parentId":"wrk_9321f175ca9445e68473262f6ca4de17","modified":1722355191198,"created":1722355191198,"name":"Produto","description":"","environment":{},"environmentPropertyOrder":null,"metaSortKey":-1722355191198,"_type":"request_group"},{"_id":"wrk_9321f175ca9445e68473262f6ca4de17","parentId":null,"modified":1722349497562,"created":1722349497562,"name":"Minerva","description":"","scope":"collection","_type":"workspace"},{"_id":"req_8c7f187eb71c4ee7a0a0c8a451c05063","parentId":"fld_7eb1d9f0f3264eba9f8747ac46d1040f","modified":1722373284530,"created":1722355203847,"url":"http://localhost:4000/produtos","name":"Alterar Produto","description":"","method":"PUT","body":{"mimeType":"application/json","text":"{\n\t  \"id\": 3,\n    \"nome\": \"Introdução à lógica de programação e algoritmos\",\n    \"descricao\": \"Aprenda os fundamentos da lógica de programação e algoritmos. O curso cobre conceitos básicos de programação, como estruturas de controle e resolução de problemas, ajudando você a desenvolver habilidades para criar soluções eficientes e organizar o raciocínio lógico necessário para programar.\",\n    \"preco\": 29.90,\n    \"duracao\": 60,\n\t  \"foto\": \"https://ik.imagekit.io/netdmdufko/logica.jpg?updatedAt=1722359434707\",\n\t\"categoria\": {\n\t\"id\": 1\n}\n}"},"parameters":[],"headers":[{"name":"Content-Type","value":"application/json"},{"name":"User-Agent","value":"insomnia/9.3.2"}],"authentication":{},"metaSortKey":-1722355203847,"isPrivate":false,"pathParameters":[],"settingStoreCookies":true,"settingSendCookies":true,"settingDisableRenderRequestBody":false,"settingEncodeUrl":true,"settingRebuildPath":true,"settingFollowRedirects":"global","_type":"request"},{"_id":"req_4b8c50d2594e447bbfe0b8bebb3780b6","parentId":"fld_7eb1d9f0f3264eba9f8747ac46d1040f","modified":1722373298424,"created":1722355201943,"url":"http://localhost:4000/produtos/3","name":"Excluir Produto","description":"","method":"DELETE","body":{"mimeType":"application/json","text":""},"parameters":[],"headers":[{"name":"Content-Type","value":"application/json"},{"name":"User-Agent","value":"insomnia/9.3.2"}],"authentication":{},"metaSortKey":-1722355201943,"isPrivate":false,"pathParameters":[],"settingStoreCookies":true,"settingSendCookies":true,"settingDisableRenderRequestBody":false,"settingEncodeUrl":true,"settingRebuildPath":true,"settingFollowRedirects":"global","_type":"request"},{"_id":"req_4feee18f7e4b4274916fbef9eead3a94","parentId":"fld_7eb1d9f0f3264eba9f8747ac46d1040f","modified":1722373310767,"created":1722355200480,"url":"http://localhost:4000/produtos","name":"Consultar todos","description":"","method":"GET","body":{},"parameters":[],"headers":[{"name":"User-Agent","value":"insomnia/9.3.2"}],"authentication":{},"metaSortKey":-1722355200480,"isPrivate":false,"pathParameters":[],"settingStoreCookies":true,"settingSendCookies":true,"settingDisableRenderRequestBody":false,"settingEncodeUrl":true,"settingRebuildPath":true,"settingFollowRedirects":"global","_type":"request"},{"_id":"req_d4e1b84329c24db39b9bf0b067ffc90a","parentId":"fld_7eb1d9f0f3264eba9f8747ac46d1040f","modified":1722373324929,"created":1722355198680,"url":"","name":"Consultar ID","description":"","method":"GET","body":{},"parameters":[],"headers":[{"name":"User-Agent","value":"insomnia/9.3.2"}],"authentication":{},"metaSortKey":-1722355198680,"isPrivate":false,"settingStoreCookies":true,"settingSendCookies":true,"settingDisableRenderRequestBody":false,"settingEncodeUrl":true,"settingRebuildPath":true,"settingFollowRedirects":"global","_type":"request"},{"_id":"req_93d2fc5d4a58495d90bf293a29e6b945","parentId":"fld_7eb1d9f0f3264eba9f8747ac46d1040f","modified":1722373339638,"created":1722355196181,"url":"","name":"Consultar nome","description":"","method":"GET","body":{},"parameters":[],"headers":[{"name":"User-Agent","value":"insomnia/9.3.2"}],"authentication":{},"metaSortKey":-1722355196181,"isPrivate":false,"settingStoreCookies":true,"settingSendCookies":true,"settingDisableRenderRequestBody":false,"settingEncodeUrl":true,"settingRebuildPath":true,"settingFollowRedirects":"global","_type":"request"},{"_id":"req_293933af4d634344bb3d56941578cbca","parentId":"fld_9c9330c0d9cb4754bcdc6b4503a6a617","modified":1722373353839,"created":1722273436738,"url":"http://localhost:4000/categorias","name":"Cadastrar Categoria","description":"","method":"POST","body":{"mimeType":"application/json","text":"{\n\t\n}"},"parameters":[],"headers":[{"name":"Content-Type","value":"application/json"},{"name":"User-Agent","value":"insomnia/9.3.2"}],"authentication":{},"metaSortKey":-1721826693371,"isPrivate":false,"pathParameters":[],"settingStoreCookies":true,"settingSendCookies":true,"settingDisableRenderRequestBody":false,"settingEncodeUrl":true,"settingRebuildPath":true,"settingFollowRedirects":"global","_type":"request"},{"_id":"fld_9c9330c0d9cb4754bcdc6b4503a6a617","parentId":"wrk_9321f175ca9445e68473262f6ca4de17","modified":1722274059085,"created":1722273436736,"name":"Categoria","description":"","environment":{},"environmentPropertyOrder":null,"metaSortKey":-1721826659192,"_type":"request_group"},{"_id":"req_83c8f398b6e4449ba48efd731b376a94","parentId":"fld_9c9330c0d9cb4754bcdc6b4503a6a617","modified":1722373354414,"created":1722273436747,"url":"localhost:4000/categorias","name":"Listar todas Categorias","description":"","method":"GET","body":{"mimeType":"application/json","text":""},"parameters":[],"headers":[{"name":"Content-Type","value":"application/json"},{"name":"User-Agent","value":"insomnia/9.3.2"}],"authentication":{},"metaSortKey":-1721826693321,"isPrivate":false,"pathParameters":[],"settingStoreCookies":true,"settingSendCookies":true,"settingDisableRenderRequestBody":false,"settingEncodeUrl":true,"settingRebuildPath":true,"settingFollowRedirects":"global","_type":"request"},{"_id":"req_68a795d7e66643d2b83a2548679e823e","parentId":"fld_9c9330c0d9cb4754bcdc6b4503a6a617","modified":1722273802138,"created":1722273436745,"url":"localhost:4000/categorias/tipo/tip","name":"Consultar Categoria por tipo","description":"","method":"GET","body":{},"parameters":[],"headers":[{"name":"User-Agent","value":"insomnia/9.3.2"}],"authentication":{},"metaSortKey":-1721826693271,"isPrivate":false,"pathParameters":[],"settingStoreCookies":true,"settingSendCookies":true,"settingDisableRenderRequestBody":false,"settingEncodeUrl":true,"settingRebuildPath":true,"settingFollowRedirects":"global","_type":"request"},{"_id":"req_c96b80b39cdd462ca1e7a4f95cd2fec2","parentId":"fld_9c9330c0d9cb4754bcdc6b4503a6a617","modified":1722273901196,"created":1722273436739,"url":"localhost:4000/categorias/1","name":"Listar Categoria por ID","description":"","method":"GET","body":{},"parameters":[],"headers":[{"name":"User-Agent","value":"insomnia/9.3.2"}],"authentication":{},"metaSortKey":-1721826693171,"isPrivate":false,"pathParameters":[],"settingStoreCookies":true,"settingSendCookies":true,"settingDisableRenderRequestBody":false,"settingEncodeUrl":true,"settingRebuildPath":true,"settingFollowRedirects":"global","_type":"request"},{"_id":"req_e8b1b84aa74a4b7e8014402f32b8bb6c","parentId":"fld_9c9330c0d9cb4754bcdc6b4503a6a617","modified":1722273944961,"created":1722273436741,"url":"localhost:4000/categorias","name":"Atualizar Categoria","description":"","method":"PUT","body":{"mimeType":"application/json","text":"{\n\t\"id\": 1,\n\t\"tipo\": \"Tipo teste atualizado\",\n\t\"descricao\": \"descrição atualizada\"\n\n}"},"parameters":[],"headers":[{"name":"Content-Type","value":"application/json"},{"name":"User-Agent","value":"insomnia/9.3.2"}],"authentication":{},"metaSortKey":-1721826693071,"isPrivate":false,"pathParameters":[],"settingStoreCookies":true,"settingSendCookies":true,"settingDisableRenderRequestBody":false,"settingEncodeUrl":true,"settingRebuildPath":true,"settingFollowRedirects":"global","_type":"request"},{"_id":"req_bd4ed80afdb94b97afaeade2cb2c354b","parentId":"fld_9c9330c0d9cb4754bcdc6b4503a6a617","modified":1722350684895,"created":1722273436744,"url":"localhost:4000/categorias/1","name":"Deletar Categoria","description":"","method":"DELETE","body":{},"parameters":[],"headers":[{"name":"User-Agent","value":"insomnia/9.3.2"}],"authentication":{},"metaSortKey":-1721826692971,"isPrivate":false,"pathParameters":[],"settingStoreCookies":true,"settingSendCookies":true,"settingDisableRenderRequestBody":false,"settingEncodeUrl":true,"settingRebuildPath":true,"settingFollowRedirects":"global","_type":"request"},{"_id":"env_9e806fbd3f4c45d5a717a62a158901a7","parentId":"wrk_9321f175ca9445e68473262f6ca4de17","modified":1722273436700,"created":1722273436700,"name":"Base Environment","data":{},"dataPropertyOrder":null,"color":null,"isPrivate":false,"metaSortKey":1721738431380,"_type":"environment"},{"_id":"jar_8985c26423c74265b710e18540061bb5","parentId":"wrk_9321f175ca9445e68473262f6ca4de17","modified":1722273436702,"created":1722273436702,"name":"Default Jar","cookies":[],"_type":"cookie_jar"}]}